factodiagrams/__init__.py
factodiagrams/preprocess/Factorisation.py
factodiagrams/preprocess/__init__.py
factodiagrams/preprocess/decomposition.py
factodiagrams/preprocess/facto_f_W.py
factodiagrams/preprocess/facto_methode.py
factodiagrams/vis/__init__.py
factodiagrams/vis/animation.py
factodiagrams/vis/points.py
factodiagrams-1.0.dist-info/METADATA
factodiagrams-1.0.dist-info/WHEEL
factodiagrams-1.0.dist-info/top_level.txt
factodiagrams-1.0.dist-info/RECORD
