Metadata-Version: 2.1
Name: factodiagrams
Version: 1.0
Summary: Visualization of prime factorization
Home-page: https://github.com/nguyenlouis/number-factorization-diagrams
Author: Bouthayna Hayou, Juliette Lidoine, Louis Nguyen, Sidy Sow.
Author-email: bouthayna.hayou@etu.umontpellier.fr , juliette.lidoine@etu.umontpellier.fr
License: MIT
Platform: UNKNOWN
